pandora_cas/__init__.py
pandora_cas/account.py
pandora_cas/data.py
pandora_cas/device.py
pandora_cas/enums.py
pandora_cas/errors.py
pandora_cas-0.0.16.dist-info/LICENSE
pandora_cas-0.0.16.dist-info/METADATA
pandora_cas-0.0.16.dist-info/WHEEL
pandora_cas-0.0.16.dist-info/RECORD
