Metadata-Version: 2.3
Name: pandora-cas
Version: 0.0.16
Summary: Pandora Car Alarm System clientside API implementation
License: MIT
Keywords: pandora,car,alarm,system,alarmtrade
Author: Alexander Ryazanov
Author-email: alryaz@alryaz.com
Requires-Python: >=3.10,<4.0
Classifier: Development Status :: 3 - Alpha
Classifier: Intended Audience :: Developers
Classifier: License :: OSI Approved :: MIT License
Classifier: Operating System :: OS Independent
Classifier: Programming Language :: Python :: 3
Classifier: Programming Language :: Python :: 3.10
Classifier: Programming Language :: Python :: 3.11
Classifier: Programming Language :: Python :: 3.12
Classifier: Programming Language :: Python :: 3.13
Classifier: Programming Language :: Python :: 3 :: Only
Classifier: Topic :: Software Development :: Libraries
Requires-Dist: aiohttp
Requires-Dist: attrs
Project-URL: Bug Reports, https://github.com/alryaz/python-pandora-cas/issues
Project-URL: Documentation, https://github.com/alryaz/python-pandora-cas
Project-URL: Homepage, https://github.com/alryaz/python-pandora-cas
Project-URL: Repository, https://github.com/alryaz/python-pandora-cas
